flit_core/__init__.py
flit_core/build_thyself.py
flit_core/buildapi.py
flit_core/common.py
flit_core/inifile.py
flit_core/sdist.py
flit_core/versionno.py
flit_core/wheel.py
flit_core/tests/__init__.py
flit_core/tests/test_build_thyself.py
flit_core/tests/test_buildapi.py
flit_core/tests/test_common.py
flit_core/tests/test_inifile.py
flit_core/tests/test_sdist.py
flit_core/tests/test_versionno.py
flit_core/tests/samples/EG_README.rst
flit_core/tests/samples/altdistname.ini
flit_core/tests/samples/bad-description-ext.toml
flit_core/tests/samples/classifiers_with_space.ini
flit_core/tests/samples/console_entry_points.txt
flit_core/tests/samples/entrypoints_conflict.ini
flit_core/tests/samples/entrypoints_missing.ini
flit_core/tests/samples/entrypoints_valid.ini
flit_core/tests/samples/extras-dev-conflict.toml
flit_core/tests/samples/extras.toml
flit_core/tests/samples/invalid_classifier.ini
flit_core/tests/samples/invalid_version1.py
flit_core/tests/samples/missing-description-file.toml
flit_core/tests/samples/misspelled-key.ini
flit_core/tests/samples/module1-pkg.ini
flit_core/tests/samples/module1-pkg.toml
flit_core/tests/samples/module1.py
flit_core/tests/samples/module2.py
flit_core/tests/samples/moduleunimportable.py
flit_core/tests/samples/modulewithconstructedversion.py
flit_core/tests/samples/my-description.rst
flit_core/tests/samples/no_docstring-pkg.toml
flit_core/tests/samples/no_docstring.py
flit_core/tests/samples/package1-pkg.ini
flit_core/tests/samples/requires-dev.toml
flit_core/tests/samples/requires-envmark.toml
flit_core/tests/samples/requires-extra-envmark.toml
flit_core/tests/samples/requires-requests.toml
flit_core/tests/samples/requires_with_empty_lines.ini
flit_core/tests/samples/some_entry_points.txt
flit_core/tests/samples/conflicting_modules/module1.py
flit_core/tests/samples/conflicting_modules/pyproject.toml
flit_core/tests/samples/conflicting_modules/src/module1.py
flit_core/tests/samples/inclusion/module1.py
dflit_core-2.3.0.1.dist-info/WHEEL
dflit_core-2.3.0.1.dist-info/METADATA
dflit_core-2.3.0.1.dist-info/RECORD
