Metadata-Version: 2.1
Name: dflit_core
Version: 2.3.0.1
Summary: Distribution-building parts of Flit. See flit package for more information
Home-page: https://github.com/davidfritzsche/dflit
License: UNKNOWN
Author: David Fritzsche / flit_core by Thomas Kluyver & contributors
Author-email: david.fritzsche@mvua.de
Requires-Python: >=2.7, !=3.0, !=3.1, !=3.2, != 3.3
Classifier: License :: OSI Approved :: BSD License
Classifier: Topic :: Software Development :: Libraries :: Python Modules
Requires-Dist: pytoml
